helm_yaml_tui/__init__.py
helm_yaml_tui/components.py
helm_yaml_tui/helm_yaml_tui.css
helm_yaml_tui/loader.py
helm_yaml_tui/main.py
helm_yaml_tui-0.2.2.dist-info/entry_points.txt
helm_yaml_tui-0.2.2.dist-info/LICENSE
helm_yaml_tui-0.2.2.dist-info/WHEEL
helm_yaml_tui-0.2.2.dist-info/METADATA
helm_yaml_tui-0.2.2.dist-info/RECORD
